Metadata-Version: 2.1
Name: ccda-processor
Version: 0.0.3
Summary: A light-weight package to process a compressed file of CCDA medical records and convert to 1 web page per patient record
Home-page: UNKNOWN
Author: Ali H Syed
Author-email: 
License: UNKNOWN
Platform: UNKNOWN
Classifier: Programming Language :: Python :: 3
Classifier: License :: OSI Approved :: MIT License
Classifier: Operating System :: OS Independent
Requires-Python: >=3.6
